MGD_Outliers.py
MGD_Outliers-0.1.4.dist-info/LICENSE
MGD_Outliers-0.1.4.dist-info/METADATA
MGD_Outliers-0.1.4.dist-info/WHEEL
MGD_Outliers-0.1.4.dist-info/top_level.txt
MGD_Outliers-0.1.4.dist-info/RECORD
