Metadata-Version: 2.1
Name: MGD-Outliers
Version: 0.1.4
Summary: MGD_Outliers is a Pypyththon package for identifying and visualizing outliers in a DataFrame.
Home-page: UNKNOWN
Author: Mayur Dushetwar
Author-email: <mdushetwar@gmail.com>
License: Apache License 2.0
Keywords: python,dataframe,outlier,outliers,inter quartile range,plot outliers,count outliers,data processing,drop outliers
Platform: UNKNOWN
Classifier: Programming Language :: Python :: 3
Classifier: License :: OSI Approved :: Apache Software License
Classifier: Operating System :: Unix
Classifier: Operating System :: MacOS :: MacOS X
Classifier: Operating System :: Microsoft :: Windows
Requires-Python: >= 3.9.7
License-File: LICENSE
Requires-Dist: numpy
Requires-Dist: pandas
Requires-Dist: matplotlib
Requires-Dist: seaborn
Requires-Dist: jinja2
